moderatefocus/__init__.py
moderatefocus/main.py
moderatefocus/prompts.py
moderatefocus-2025.12.21103715.dist-info/METADATA
moderatefocus-2025.12.21103715.dist-info/WHEEL
moderatefocus-2025.12.21103715.dist-info/top_level.txt
moderatefocus-2025.12.21103715.dist-info/RECORD
