Metadata-Version: 2.4
Name: moderatefocus
Version: 2025.12.21103715
Summary: A new package that analyzes user-submitted text queries about community moderation or platform policies (like why small voting projects get flagged) and returns structured insights. It uses an LLM to 
Author-email: moderatefocus <hi@eugene.plus>
License: MIT
Project-URL: Homepage, https://github.com/chigwell/moderatefocus
Requires-Python: >=3.9
Requires-Dist: langchain-llm7>=0.0.0
Requires-Dist: llmatch-messages>=0.0.0
Requires-Dist: langchain-core>=0.3.0
